lumos/__init__.py
lumos_ml-0.0.1.dist-info/METADATA
lumos_ml-0.0.1.dist-info/WHEEL
lumos_ml-0.0.1.dist-info/top_level.txt
lumos_ml-0.0.1.dist-info/RECORD
