Metadata-Version: 2.4
Name: lumos-ml
Version: 0.0.1
Summary: Illuminating machine learning workflows
Author-email: Tim Marquart <tmarquart@gmail.com>
License: MIT
Classifier: Development Status :: 1 - Planning
Classifier: Intended Audience :: Developers
Classifier: License :: OSI Approved :: Apache Software License
Classifier: Programming Language :: Python :: 3
Classifier: Topic :: Scientific/Engineering :: Artificial Intelligence
Requires-Python: >=3.9
